powergrasp/__init__.py
powergrasp/__main__.py
powergrasp/asp.py
powergrasp/cli.py
powergrasp/constants.py
powergrasp/edge_filtering.py
powergrasp/graph.py
powergrasp/metrics.py
powergrasp/motif.py
powergrasp/motif_batch.py
powergrasp/recipe.py
powergrasp/routines.py
powergrasp/searchers.py
powergrasp/utils.py
powergrasp/asp/block-constraint-cpu.lp
powergrasp/asp/block-constraint-memory.lp
powergrasp/asp/extract-ccs.lp
powergrasp/asp/process-motif.lp
powergrasp/asp/scoring_powergraph.lp
powergrasp/asp/search-biclique.lp
powergrasp/asp/search-clique.lp
powergrasp/asp/search-fullbiclique.lp
powergrasp/asp/search-star.lp
powergrasp-0.8.18.dist-info/METADATA
powergrasp-0.8.18.dist-info/RECORD
powergrasp-0.8.18.dist-info/WHEEL
powergrasp-0.8.18.dist-info/entry_points.txt
powergrasp-0.8.18.dist-info/top_level.txt
