Metadata-Version: 2.1
Name: powergrasp
Version: 0.8.18
Summary: compress graphs with answer-set-programming
Home-page: https://github.com/aluriak/powergrasp
Author: Lucas Bourneuf
Author-email: lucas.bourneuf@inria.fr
License: GPL
Keywords: graph,Answer Set Programming
Platform: UNKNOWN
Classifier: Development Status :: 2 - Pre-Alpha
Classifier: Intended Audience :: Science/Research
Classifier: License :: OSI Approved :: GNU General Public License (GPL)
Classifier: Natural Language :: English
Classifier: Programming Language :: Python :: 3
Classifier: Programming Language :: Python :: 3.5
Classifier: Programming Language :: ASP
Classifier: Topic :: Software Development :: Libraries :: Python Modules
Requires-Dist: bubbletools (>=0.6.1)
Requires-Dist: clyngor (>=0.3.12)
Requires-Dist: networkx (>=2.1)
Requires-Dist: phasme (>=0.0.11)
Requires-Dist: pytest (>=3.5.0)
